Metadata-Version: 2.1
Name: InnoFileManager
Version: 0.2
Summary: Easy way to manage files
Home-page: https://github.com/AmZakirov/FileManager
Author: AmZakirov
Author-email: am.zakirov@innopolis.university
